contextual/__init__.py
contextual/contextual_api_client.py
ctxl_ai-0.2.1.dist-info/METADATA
ctxl_ai-0.2.1.dist-info/WHEEL
ctxl_ai-0.2.1.dist-info/top_level.txt
ctxl_ai-0.2.1.dist-info/RECORD
