Metadata-Version: 2.1
Name: ctxl-ai
Version: 0.2.1
Summary: Python SDK for Contextual AI Platform
Requires-Python: >=3.8
Requires-Dist: requests >=2.32.3
